delamain/__init__.py
delamain/app.py
delamain/cli.py
delamain/config.py
delamain/log.py
delamain/agents/__init__.py
delamain/agents/base.py
delamain/agents/executor.py
delamain/agents/utils.py
delamain/agents/mas/__init__.py
delamain/agents/mas/agent.py
delamain/agents/mas/tools.py
delamain/agents/mas/prompts/executor_system_prompt.md
delamain/agents/mas/prompts/manage_system_prompt.md
delamain/agents/mas/prompts/planner_system_prompt.md
delamain/agents/mas/prompts/summarizer_system_prompt.md
delamain/agents/mas/prompts/validator_system_prompt.md
delamain/agents/react/__init__.py
delamain/agents/react/agent.py
delamain/agents/react/prompts/executor_system_prompt.md
delamain/agents/react/prompts/reasoning_system_prompt.md
delamain/agents/wrapper/__init__.py
delamain/agents/wrapper/agent.py
delamain/agents/wrapper/prompts/executor_system_prompt.md
delamain/routers/__init__.py
delamain/routers/anthropic.py
delamain/routers/openai.py
delamain-0.0.3.dist-info/METADATA
delamain-0.0.3.dist-info/WHEEL
delamain-0.0.3.dist-info/entry_points.txt
delamain-0.0.3.dist-info/licenses/LICENSE
delamain-0.0.3.dist-info/RECORD
