Metadata-Version: 2.4
Name: Delamain
Version: 0.0.3
Summary: Re-Act Agents with OpenAI/Anthropic compatible api
Project-URL: Homepage, https://ai-zerolab.github.io/Delamain/
Project-URL: Repository, https://github.com/ai-zerolab/Delamain
Project-URL: Documentation, https://ai-zerolab.github.io/Delamain/
Author-email: Wh1isper <jizhongsheng957@gmail.com>
License-File: LICENSE
Keywords: python
Classifier: Intended Audience :: Developers
Classifier: Programming Language :: Python
Classifier: Programming Language :: Python :: 3
Classifier: Programming Language :: Python :: 3.10
Classifier: Programming Language :: Python :: 3.11
Classifier: Programming Language :: Python :: 3.12
Classifier: Programming Language :: Python :: 3.13
Classifier: Topic :: Software Development :: Libraries :: Python Modules
Requires-Python: <4.0,>=3.10
Requires-Dist: anthropic>=0.49.0
Requires-Dist: boto3>=1.37.18
Requires-Dist: botocore>=1.37.18
Requires-Dist: click>=8.1.8
Requires-Dist: fastapi[standard]>=0.115.12
Requires-Dist: jinja2>=3.1.6
Requires-Dist: loguru>=0.7.3
Requires-Dist: pydantic-ai>=0.0.44
Requires-Dist: pydantic-settings>=2.8.1
Requires-Dist: pydantic>=2.10.6
Requires-Dist: sse-starlette>=2.2.1
Requires-Dist: uvicorn[standard]>=0.34.0
